iduconfig/__init__.py
iduconfig/_version.py
iduconfig/config.py
idu_config-1.0.3.dist-info/METADATA
idu_config-1.0.3.dist-info/WHEEL
idu_config-1.0.3.dist-info/RECORD
