Metadata-Version: 2.3
Name: IDU-config
Version: 1.0.3
Summary: --/--
License: BSD-3-Clause
Author: soldey
Author-email: 71354808+soldey@users.noreply.github.com
Requires-Python: >=3.10,<3.13
Classifier: License :: OSI Approved :: BSD License
Classifier: Programming Language :: Python :: 3
Classifier: Programming Language :: Python :: 3.10
Classifier: Programming Language :: Python :: 3.11
Classifier: Programming Language :: Python :: 3.12
Requires-Dist: loguru (>=0.7.0,<0.8.0)
Requires-Dist: python-dotenv (>=1.0.1,<2.0.0)
